{
  "at_utc": "2026-07-22T18:11:10+00:00",
  "base_url": "https://trendflow-site.vercel.app",
  "briefings_live": 121,
  "ai_infra_pages_live": 32,
  "sponsor_cards_compliant": 32,
  "hub_live_and_compliant": true,
  "hub_listed_briefings": 32,
  "footer_sponsor_compliant": true,
  "sponsor_touchpoints_total": 34,
  "mingxin_landing_http": 200,
  "problems": [],
  "note": "click/conversion data is measured on the MingXin side via UTM (utm_source=trendflow); this monitor covers supply-side exposure and compliance only"
}